{
  "Error_InvalidCredentials": "Credenciales inválidas.",
  "Error_UserInactive": "Usuario inactivo o prohibido.",
  "Error_EmailExists": "El email ya está registrado.",
  "Error_EmailAlreadyExists": "El email ya está registrado.",
  "Error_PasswordTooShort": "La contraseña debe tener al menos 6 caracteres.",
  "Error_NicknameExists": "El nickname ya está registrado.",
  "Error_InvalidData": "Datos inválidos.",
  "Error_UserNotFound": "Usuario no encontrado.",
  "Error_SessionNotFound": "Sesión no encontrada.",
  "Error_PreferencesExist": "Las preferencias ya existen para este usuario.",
  "Error_PreferencesInvalid": "Las preferencias proporcionadas no son válidas.",
  "Error_PreferencesUpdate": "No se pudo actualizar las preferencias.",
  "Error_PreferencesDelete": "No se pudo eliminar las preferencias.",
  "Error_PreferencesUnauthorized": "No tienes permisos para modificar estas preferencias.",
  "Error_PreferencesNotFound": "Preferencias no encontradas.",
  "Error_InternalServer": "Ha ocurrido un error internal inesperado.",
  "Error_DeleteAllData": "Error al eliminar todos los datos. Operación cancelada.",
  "Success_UserCreated": "Usuario creado exitosamente.",
  "Success_UserRegistered": "Usuario registrado exitosamente. Por favor confirma tu email.",
  "Success_UserFound": "Usuario encontrado.",
  "Success_UserUpdated": "Usuario actualizado exitosamente.",
  "Success_UserDeleted": "Usuario eliminado exitosamente.",
  "Success_ListUsers": "Lista de usuarios obtenida exitosamente.",
  "Success_Login": "Login exitoso.",
  "Success_PasswordReset": "Contraseña restablecida exitosamente.",
  "Success_EmailConfirmed": "Email confirmado exitosamente.",
  "Success_SessionFound": "Sesión encontrada.",
  "Success_SessionDeleted": "Sesión eliminada exitosamente.",
  "Success_PreferencesCreated": "Preferencias creadas exitosamente.",
  "Success_PreferencesFound": "Preferencias encontradas.",
  "Success_PreferencesUpdated": "Preferencias actualizadas exitosamente.",
  "Success_PreferencesAndUserUpdated": "Preferencias y usuario actualizados exitosamente.",
  "Success_UserAndPreferencesCreated": "Usuario y preferencias creados exitosamente.",
  "Success_Logout": "Logout exitoso. Todas las sesiones han sido eliminadas y el último acceso ha sido reiniciado.",
  "Success_PreferencesDeleted": "Preferencias eliminadas exitosamente.",
  "Success_UserAndPreferencesUpdated": "Usuario y preferencias actualizados exitosamente.",
  "Success_AllDataDeleted": "Todos los datos (usuarios, preferencias y sesiones) han sido eliminados exitosamente. Base de datos limpia."
}